paylix/__init__.py
paylix/test.py
paylix/resources/__init__.py
paylix/resources/blacklist.py
paylix/resources/categories.py
paylix/resources/coupons.py
paylix/resources/customers.py
paylix/resources/feedback.py
paylix/resources/groups.py
paylix/resources/orders.py
paylix/resources/payments.py
paylix/resources/products.py
paylix/resources/queries.py
paylix/resources/subscriptions.py
paylix/resources/whitelists.py
paylix-1.0.1.dist-info/METADATA
paylix-1.0.1.dist-info/WHEEL
paylix-1.0.1.dist-info/top_level.txt
paylix-1.0.1.dist-info/RECORD
