Metadata-Version: 2.4
Name: Paylix
Version: 1.0.1
Summary: Official Paylix Python SDK
Home-page: https://github.com/Dboosts2/paylix-python-sdk
Author: Paylix
Author-email: you@example.com
Classifier: Programming Language :: Python :: 3
Classifier: Operating System :: OS Independent
Classifier: License :: OSI Approved :: MIT License
Requires-Python: >=3.7
Requires-Dist: requests
Dynamic: author
Dynamic: author-email
Dynamic: classifier
Dynamic: description
Dynamic: description-content-type
Dynamic: home-page
Dynamic: requires-dist
Dynamic: requires-python
Dynamic: summary
